echoai/__init__.py
echoai/main.py
echoai/clients/__init__.py
echoai/clients/langchain_client.py
echoai/clients/openai_client.py
echoai_dev-0.2.1.dist-info/LICENSE.txt
echoai_dev-0.2.1.dist-info/METADATA
echoai_dev-0.2.1.dist-info/WHEEL
echoai_dev-0.2.1.dist-info/entry_points.txt
echoai_dev-0.2.1.dist-info/top_level.txt
echoai_dev-0.2.1.dist-info/RECORD
