Metadata-Version: 2.1
Name: echoai-dev
Version: 0.2.1
Summary: The command line tool to interface with Generative AI.
Author: Fabio Dr.No Nonato
Author-email: echoaidev@gmail.com
Classifier: Programming Language :: Python :: 3
Classifier: License :: OSI Approved :: MIT License
Classifier: Operating System :: OS Independent
License-File: LICENSE.txt
Requires-Dist: openai
Requires-Dist: pygments
Requires-Dist: langchain
Requires-Dist: boto3
